LICENSE
MANIFEST.in
README.md
requirements.txt
setup.cfg
setup.py
mp_starter/__init__.py
mp_starter.egg-info/PKG-INFO
mp_starter.egg-info/SOURCES.txt
mp_starter.egg-info/dependency_links.txt
mp_starter.egg-info/entry_points.txt
mp_starter.egg-info/not-zip-safe
mp_starter.egg-info/requires.txt
mp_starter.egg-info/top_level.txt
mp_starter/cli/__init__.py
mp_starter/cli/bootstrap.py
mp_starter/cli/main.py
mp_starter/cli/controllers/__init__.py
mp_starter/cli/controllers/base.py
mp_starter/cli/controllers/django.py
mp_starter/cli/ext/__init__.py
mp_starter/cli/plugins/__init__.py
mp_starter/cli/plugins/example.py
mp_starter/cli/templates/__init__.py
mp_starter/core/__init__.py
mp_starter/core/exc.py
mp_starter/utils/__init__.py
mp_starter/utils/test.py