Metadata-Version: 1.1
Name: mp-starter
Version: 0.1
Summary: mp-mp_starter is a lib to optimize my workflow when starting a project.Creating the project and its skeleton.
Home-page: https://github.com/mrlucascardoso/mp-starter
Author: Lucas Cardoso
Author-email: mr.lucascardoso@gmail.com
License: BSD
Keywords: mp_starter,django,project
Platform: UNKNOWN
Classifier: Development Status :: 4 - Beta
Classifier: Intended Audience :: Developers
Classifier: License :: OSI Approved :: BSD License
Classifier: Natural Language :: English
Classifier: Natural Language :: Portuguese
Classifier: Operating System :: OS Independent
Classifier: Programming Language :: Python :: 3
Classifier: Programming Language :: Python
Classifier: Topic :: Software Development :: Libraries :: Python Modules
Classifier: Topic :: Software Development :: Testing
Classifier: Topic :: Utilities
